langchain_hreflang/__init__.py
langchain_hreflang/client.py
langchain_hreflang/exceptions.py
langchain_hreflang/tools.py
langchain_hreflang-0.1.0.dist-info/licenses/LICENSE
tests/__init__.py
tests/conftest.py
tests/test_basic.py
langchain_hreflang-0.1.0.dist-info/METADATA
langchain_hreflang-0.1.0.dist-info/WHEEL
langchain_hreflang-0.1.0.dist-info/top_level.txt
langchain_hreflang-0.1.0.dist-info/RECORD
