Metadata-Version: 2.4
Name: langchain-hreflang
Version: 0.1.0
Summary: LangChain tools for hreflang SEO analysis using hreflang.org API
Home-page: https://github.com/diffen/langchain-hreflang
Author: Nick Jasuja
Author-email: Nick Jasuja <nikhilesh@gmail.com>
License: MIT License
Project-URL: Homepage, https://github.com/diffen/langchain-hreflang
Project-URL: Documentation, https://github.com/diffen/langchain-hreflang#readme
Project-URL: Repository, https://github.com/diffen/langchain-hreflang.git
Project-URL: Bug Reports, https://github.com/diffen/langchain-hreflang/issues
Project-URL: Changelog, https://github.com/diffen/langchain-hreflang/blob/main/CHANGELOG.md
Keywords: langchain,hreflang,seo,international,ai,agents,crewai
Classifier: Development Status :: 4 - Beta
Classifier: Intended Audience :: Developers
Classifier: License :: OSI Approved :: MIT License
Classifier: Operating System :: OS Independent
Classifier: Programming Language :: Python :: 3
Classifier: Programming Language :: Python :: 3.12
Classifier: Programming Language :: Python :: 3.13
Requires-Python: >=3.12
License-File: LICENSE
Requires-Dist: langchain>=0.1.0
Requires-Dist: requests>=2.25.0
Requires-Dist: pydantic>=2.0.0
Requires-Dist: python-dotenv>=0.19.0
Provides-Extra: dev
Requires-Dist: pytest>=6.0; extra == "dev"
Requires-Dist: pytest-cov>=2.0; extra == "dev"
Requires-Dist: black>=21.0; extra == "dev"
Requires-Dist: flake8>=3.8; extra == "dev"
Requires-Dist: mypy>=0.800; extra == "dev"
Requires-Dist: twine>=3.0; extra == "dev"
Requires-Dist: build>=0.7; extra == "dev"
Requires-Dist: python-dotenv>=0.19.0; extra == "dev"
Provides-Extra: crewai
Requires-Dist: crewai>=0.1.0; extra == "crewai"
Provides-Extra: all
Requires-Dist: crewai>=0.1.0; extra == "all"
Requires-Dist: pytest>=6.0; extra == "all"
Requires-Dist: black>=21.0; extra == "all"
Dynamic: author
Dynamic: home-page
Dynamic: license-file
Dynamic: requires-python
